odoo10_addon_sale_order_line_variant_description-10.0.1.0.0-py2.7-nspkg.pth
odoo/addons/sale_order_line_variant_description/README.rst
odoo/addons/sale_order_line_variant_description/__init__.py
odoo/addons/sale_order_line_variant_description/__manifest__.py
odoo/addons/sale_order_line_variant_description/i18n/ca.po
odoo/addons/sale_order_line_variant_description/i18n/de.po
odoo/addons/sale_order_line_variant_description/i18n/el_GR.po
odoo/addons/sale_order_line_variant_description/i18n/es.po
odoo/addons/sale_order_line_variant_description/i18n/es_ES.po
odoo/addons/sale_order_line_variant_description/i18n/fi.po
odoo/addons/sale_order_line_variant_description/i18n/fr.po
odoo/addons/sale_order_line_variant_description/i18n/fr_CH.po
odoo/addons/sale_order_line_variant_description/i18n/fr_FR.po
odoo/addons/sale_order_line_variant_description/i18n/gl.po
odoo/addons/sale_order_line_variant_description/i18n/hr.po
odoo/addons/sale_order_line_variant_description/i18n/hr_HR.po
odoo/addons/sale_order_line_variant_description/i18n/it.po
odoo/addons/sale_order_line_variant_description/i18n/nl.po
odoo/addons/sale_order_line_variant_description/i18n/nl_NL.po
odoo/addons/sale_order_line_variant_description/i18n/pt.po
odoo/addons/sale_order_line_variant_description/i18n/pt_BR.po
odoo/addons/sale_order_line_variant_description/i18n/ro.po
odoo/addons/sale_order_line_variant_description/i18n/ru.po
odoo/addons/sale_order_line_variant_description/i18n/sale_order_line_variant_description.pot
odoo/addons/sale_order_line_variant_description/i18n/sl.po
odoo/addons/sale_order_line_variant_description/i18n/tr.po
odoo/addons/sale_order_line_variant_description/i18n/tr_TR.po
odoo/addons/sale_order_line_variant_description/i18n/vi_VN.po
odoo/addons/sale_order_line_variant_description/i18n/zh_CN.po
odoo/addons/sale_order_line_variant_description/models/__init__.py
odoo/addons/sale_order_line_variant_description/models/product_product.py
odoo10_addon_sale_order_line_variant_description-10.0.1.0.0.dist-info/DESCRIPTION.rst
odoo10_addon_sale_order_line_variant_description-10.0.1.0.0.dist-info/METADATA
odoo10_addon_sale_order_line_variant_description-10.0.1.0.0.dist-info/RECORD
odoo10_addon_sale_order_line_variant_description-10.0.1.0.0.dist-info/WHEEL
odoo10_addon_sale_order_line_variant_description-10.0.1.0.0.dist-info/metadata.json
odoo10_addon_sale_order_line_variant_description-10.0.1.0.0.dist-info/namespace_packages.txt
odoo10_addon_sale_order_line_variant_description-10.0.1.0.0.dist-info/top_level.txt
