Metadata-Version: 2.0
Name: odoo10-addon-sale-order-line-variant-description
Version: 10.0.1.0.0
Summary: Sale order line variant description
Home-page: https://www.agilebg.com
Author: Agile Business Group, Odoo Community Association (OCA)
Author-email: support@odoo-community.org
License: AGPL-3
Platform: UNKNOWN
Classifier: Programming Language :: Python :: 2.7
Classifier: Framework :: Odoo
Classifier: License :: OSI Approved :: GNU Affero General Public License v3
Requires-Dist: odoo (<10.1dev,>=10.0)
